pg8000/__init__.py
pg8000/converters.py
pg8000/core.py
pg8000/dbapi.py
pg8000/exceptions.py
pg8000/legacy.py
pg8000/native.py
pg8000/types.py
pg8000-1.31.0.dist-info/LICENSE
pg8000-1.31.0.dist-info/METADATA
pg8000-1.31.0.dist-info/WHEEL
pg8000-1.31.0.dist-info/top_level.txt
pg8000-1.31.0.dist-info/RECORD
